setup.py
py_ryobi_gdo/__init__.py
py_ryobi_gdo.egg-info/PKG-INFO
py_ryobi_gdo.egg-info/SOURCES.txt
py_ryobi_gdo.egg-info/dependency_links.txt
py_ryobi_gdo.egg-info/requires.txt
py_ryobi_gdo.egg-info/top_level.txt