Metadata-Version: 1.0
Name: py-ryobi-gdo
Version: 0.0.27
Summary: Python package for controlling Ryobi Garage Door
Home-page: https://github.com/guillaume1410/py_ryobi_gdo
Author: Guillaume1410
Author-email: super.guillaume@gmail.com
License: MIT
Platform: UNKNOWN
